supervisor/__init__.py
supervisor/_supervisor.py
supervisor/core/__init__.py
supervisor/core/api.py
supervisor/core/interface.py
supervisor/core/orders.py
supervisor/core/settings.py
supervisor/core/trailing_orders.py
supervisor/core/ws_thread.py
supervisor/core/auth/APIKeyAuth.py
supervisor/core/auth/APIKeyAuthWithExpires.py
supervisor/core/auth/AccessTokenAuth.py
supervisor/core/auth/__init__.py
supervisor/core/utils/__init__.py
supervisor/core/utils/errors.py
supervisor/core/utils/log.py
supervisor/core/utils/math.py
bitmex_supervisor-0.7.4.dist-info/LICENSE
bitmex_supervisor-0.7.4.dist-info/METADATA
bitmex_supervisor-0.7.4.dist-info/WHEEL
bitmex_supervisor-0.7.4.dist-info/top_level.txt
bitmex_supervisor-0.7.4.dist-info/RECORD
