Metadata-Version: 2.1
Name: bitmex-supervisor
Version: 0.7.4
Summary: Automated monitoring of orders/positions on your BitMEX account.
Home-page: https://github.com/forkcs/bitmex-supervisor
Author: Fedor Soldatkin
Author-email: fsoldatkin@yandex.ru
License: MIT License
Keywords: {keywords}
Platform: any
Classifier: Development Status :: 3 - Alpha
Classifier: Intended Audience :: Developers
Classifier: License :: OSI Approved :: MIT License
Classifier: Operating System :: OS Independent
Classifier: Programming Language :: Python
Classifier: Programming Language :: Python :: 3.7
Classifier: Programming Language :: Python :: 3.8
Classifier: Topic :: Software Development :: Libraries :: Python Modules
Requires-Python: >= 3.7
Requires-Dist: certifi (==2020.4.5.1)
Requires-Dist: chardet (==3.0.4)
Requires-Dist: idna (==2.9)
Requires-Dist: requests (==2.23.0)
Requires-Dist: six (==1.14.0)
Requires-Dist: urllib3 (==1.25.9)
Requires-Dist: websocket-client (==0.56.0)
Requires-Dist: future (==0.18.)
